README.md
setup.py
dktools/__init__.py
dktools/async.py
dktools/compression.py
dktools/encryptanddecode.py
dktools/hello.py
dktools/randomk.py
dktools/timek.py
dktools.egg-info/PKG-INFO
dktools.egg-info/SOURCES.txt
dktools.egg-info/dependency_links.txt
dktools.egg-info/top_level.txt